pyqq
