Metadata-Version: 1.0
Name: pyqq
Version: 0.0.5
Summary: nsfocus qq client library
Home-page: http://github.com/kulasama/pyqq
Author: kula
Author-email: kulasama@gmail.com
License: gpl3
Platform: any
